vk_miniapp_auth/__init__.py
vk_miniapp_auth/auth.py
vk_miniapp_auth/data.py
vk_miniapp_auth/errors.py
vk_miniapp_auth/types.py
vk_mini_app_auth-1.0.3.dist-info/METADATA
vk_mini_app_auth-1.0.3.dist-info/WHEEL
vk_mini_app_auth-1.0.3.dist-info/licenses/LICENSE
vk_mini_app_auth-1.0.3.dist-info/RECORD
