Metadata-Version: 2.4
Name: vk-mini-app-auth
Version: 1.0.3
Summary: Python package that implements VK Mini Apps authentication algorithms.
License: MIT
License-File: LICENSE
Keywords: VK,VK Mini Apps,VK Bot,Poetry
Author: Dmitry Vasiliev
Author-email: contact.vasiliev.dmitry@gmail.com
Requires-Python: >=3.10,<4.0
Classifier: License :: OSI Approved :: MIT License
Classifier: Operating System :: OS Independent
Classifier: Programming Language :: Python :: 3
Classifier: Programming Language :: Python :: 3.10
Classifier: Programming Language :: Python :: 3.11
Classifier: Programming Language :: Python :: 3.12
Classifier: Programming Language :: Python :: 3.13
Classifier: Programming Language :: Python :: 3.14
Classifier: Topic :: Security
Project-URL: Documentation, https://swimmwatch.github.io/vk-mini-app-auth/
Project-URL: Homepage, https://pypi.org/project/vk-mini-app-auth/
Project-URL: Repository, https://github.com/swimmwatch/vk-mini-app-auth
